odoo/addons/sale_order_product_recommendation_product_sold_by_delivery_week/README.rst
odoo/addons/sale_order_product_recommendation_product_sold_by_delivery_week/__init__.py
odoo/addons/sale_order_product_recommendation_product_sold_by_delivery_week/__manifest__.py
odoo/addons/sale_order_product_recommendation_product_sold_by_delivery_week/i18n/es.po
odoo/addons/sale_order_product_recommendation_product_sold_by_delivery_week/i18n/it.po
odoo/addons/sale_order_product_recommendation_product_sold_by_delivery_week/i18n/sale_order_product_recommendation_product_sold_by_delivery_week.pot
odoo/addons/sale_order_product_recommendation_product_sold_by_delivery_week/readme/CONTRIBUTORS.md
odoo/addons/sale_order_product_recommendation_product_sold_by_delivery_week/readme/DESCRIPTION.md
odoo/addons/sale_order_product_recommendation_product_sold_by_delivery_week/readme/ROADMAP.md
odoo/addons/sale_order_product_recommendation_product_sold_by_delivery_week/static/description/icon.png
odoo/addons/sale_order_product_recommendation_product_sold_by_delivery_week/static/description/index.html
odoo/addons/sale_order_product_recommendation_product_sold_by_delivery_week/wizard/__init__.py
odoo/addons/sale_order_product_recommendation_product_sold_by_delivery_week/wizard/sale_order_recommendation.py
odoo/addons/sale_order_product_recommendation_product_sold_by_delivery_week/wizard/sale_order_recommendation_view.xml
odoo_addon_sale_order_product_recommendation_product_sold_by_delivery_week-18.0.1.0.0.2.dist-info/METADATA
odoo_addon_sale_order_product_recommendation_product_sold_by_delivery_week-18.0.1.0.0.2.dist-info/WHEEL
odoo_addon_sale_order_product_recommendation_product_sold_by_delivery_week-18.0.1.0.0.2.dist-info/top_level.txt
odoo_addon_sale_order_product_recommendation_product_sold_by_delivery_week-18.0.1.0.0.2.dist-info/RECORD
